jimmer/__init__.py
jimmer/client_start.py
jimmer/server_start.py
jimmer/.idea/jimmer.iml
jimmer/.idea/markdown-navigator.xml
jimmer/.idea/misc.xml
jimmer/.idea/modules.xml
jimmer/.idea/preferred-vcs.xml
jimmer/.idea/vcs.xml
jimmer/.idea/workspace.xml
jimmer/.idea/inspectionProfiles/Project_Default.xml
jimmer/.idea/markdown-navigator/profiles_settings.xml
jimmer/client/__init__.py
jimmer/client/client.py
jimmer/client/controller.py
jimmer/client/html_parser.py
jimmer/client/resources.qrc
jimmer/client/resources_rc.py
jimmer/client/storage.py
jimmer/client/view.py
jimmer/client/__pycache__/__init__.cpython-35.pyc
jimmer/client/__pycache__/client.cpython-35.pyc
jimmer/client/__pycache__/controller.cpython-35.pyc
jimmer/client/__pycache__/html_parser.cpython-35.pyc
jimmer/client/__pycache__/resources_rc.cpython-35.pyc
jimmer/client/__pycache__/storage.cpython-35.pyc
jimmer/client/__pycache__/view.cpython-35.pyc
jimmer/client/db/newUser.client.sqlite
jimmer/client/db/newUser1.client.sqlite
jimmer/client/db/newUser2.client.sqlite
jimmer/client/db/newUser3.client.sqlite
jimmer/client/images/icons/b.jpg
jimmer/client/images/icons/chat1.ico
jimmer/client/images/icons/chat1.png
jimmer/client/images/icons/chat2.ico
jimmer/client/images/icons/chat2.png
jimmer/client/images/icons/i.jpg
jimmer/client/images/icons/minus.ico
jimmer/client/images/icons/minus.png
jimmer/client/images/icons/plus.ico
jimmer/client/images/icons/plus.png
jimmer/client/images/icons/u.jpg
jimmer/client/images/smiles/bad.gif
jimmer/client/images/smiles/biggrin.gif
jimmer/client/images/smiles/blum1.gif
jimmer/client/images/smiles/blush.gif
jimmer/client/images/smiles/boredom.gif
jimmer/client/images/smiles/bye.gif
jimmer/client/images/smiles/cool.gif
jimmer/client/images/smiles/cray.gif
jimmer/client/images/smiles/dance2.gif
jimmer/client/images/smiles/drinks.gif
jimmer/client/images/smiles/empathy.gif
jimmer/client/images/smiles/fool.gif
jimmer-0.12.dist-info/DESCRIPTION.rst
jimmer-0.12.dist-info/METADATA
jimmer-0.12.dist-info/RECORD
jimmer-0.12.dist-info/WHEEL
jimmer-0.12.dist-info/metadata.json
jimmer-0.12.dist-info/top_level.txt
