Metadata-Version: 2.0
Name: jimmer
Version: 0.12
Summary: An example of messenger based on JIM protocol.
Home-page: https://github.com/ealesid/jimmer
Author: Aleksey Sidorov
Author-email: ealesid@gmail.com
License: UNKNOWN
Keywords: python,messenger,JIM,JSON IM Protocol
Platform: UNKNOWN
Requires-Python: >=3.5
Requires-Dist: PyQt5 (==5.9)
Requires-Dist: SQLAlchemy (==1.1.14)
